noctivault/__init__.py
noctivault/app/resolver.py
noctivault/cli.py
noctivault/client.py
noctivault/core/errors.py
noctivault/core/value.py
noctivault/io/enc.py
noctivault/io/fs.py
noctivault/io/yaml.py
noctivault/provider/gcp.py
noctivault/provider/local_mocks.py
noctivault/provider/protocol.py
noctivault/schema/models.py
noctivault/tree/node.py
noctivault-0.1.0.dist-info/METADATA
noctivault-0.1.0.dist-info/WHEEL
noctivault-0.1.0.dist-info/entry_points.txt
noctivault-0.1.0.dist-info/licenses/LICENSE
noctivault-0.1.0.dist-info/RECORD
