Metadata-Version: 2.4
Name: noctivault
Version: 0.1.0
Summary: Secure secret handler with cloud platform
License: MIT
License-File: LICENSE
Keywords: secret,secret-manager,vault,security
Author: ricky-rehivo
Author-email: ricky.rehivo@gmail.com
Requires-Python: >=3.10
Classifier: Development Status :: 3 - Alpha
Classifier: Intended Audience :: Developers
Classifier: License :: OSI Approved :: MIT License
Classifier: Programming Language :: Python :: 3
Classifier: Programming Language :: Python :: 3.10
Classifier: Programming Language :: Python :: 3.11
Classifier: Programming Language :: Python :: 3.12
Classifier: Programming Language :: Python :: 3.13
Classifier: Programming Language :: Python :: 3.14
Classifier: Programming Language :: Python :: 3 :: Only
Classifier: Topic :: Security :: Cryptography
Classifier: Typing :: Typed
Provides-Extra: gcp
Provides-Extra: local-enc
Requires-Dist: cryptography (>=45.0.7,<46.0.0) ; extra == "local-enc"
Requires-Dist: google-cloud-secret-manager (>=2.24.0,<3.0.0) ; extra == "gcp"
Requires-Dist: pydantic (>=2.6.0)
Requires-Dist: pyyaml (>=6.0.2,<7.0.0)
Project-URL: Changelog, https://github.com/stellavoid-org/noctivault/releases
Project-URL: Issues, https://github.com/stellavoid-org/noctivault/issues
Project-URL: Repository, https://github.com/stellavoid-org/noctivault
